xtal2txt/__init__.py
xtal2txt/analysis.py
xtal2txt/core.py
xtal2txt/decoder.py
xtal2txt/local_env.py
xtal2txt/tokenizer.py
xtal2txt/transforms.py
xtal2txt/utils.py
xtal2txt-0.1.0.dist-info/LICENSE
xtal2txt-0.1.0.dist-info/METADATA
xtal2txt-0.1.0.dist-info/NOTICE.txt
xtal2txt-0.1.0.dist-info/WHEEL
xtal2txt-0.1.0.dist-info/top_level.txt
xtal2txt-0.1.0.dist-info/RECORD
