Metadata-Version: 2.1
Name: xtal2txt
Version: 0.1.0
Summary: Package to encode and decode crystal structures into text representations
Author: Nawaf Alampara, Reza Aliakbari, Santiago Miret
Author-email: Kevin Maik Jablonka <mail@kjablonka.com>
Maintainer-email: Nawaf Alampara <nawaf.alampara@uni-jena.de>, Kevin Maik Jablonka <mail@kjablonka.com>
License: MIT License
Project-URL: Homepage, https://github.com/lamalab-org/xtal2txt
Project-URL: Issues, https://github.com/lamalab-org/xtal2txt/issues
Keywords: llm,materials,chemistry
Classifier: Development Status :: 1 - Planning
Classifier: Environment :: Console
Classifier: Intended Audience :: Developers
Classifier: License :: OSI Approved :: MIT License
Classifier: Operating System :: OS Independent
Classifier: Framework :: Pytest
Classifier: Programming Language :: Python
Classifier: Programming Language :: Python :: 3.8
Classifier: Programming Language :: Python :: 3.9
Classifier: Programming Language :: Python :: 3.10
Classifier: Programming Language :: Python :: 3.11
Classifier: Programming Language :: Python :: 3 :: Only
Requires-Python: >=3.8
License-File: LICENSE
License-File: NOTICE.txt
Requires-Dist: transformers
Requires-Dist: slices
Requires-Dist: robocrys
Requires-Dist: matminer
Requires-Dist: keras <3
Requires-Dist: pystow
Provides-Extra: decoder
Requires-Dist: pyxtal ; extra == 'decoder'
Provides-Extra: dev
Requires-Dist: pytest ; extra == 'dev'
Requires-Dist: bump-my-version ; extra == 'dev'
Provides-Extra: docs
Requires-Dist: mkdocs ; extra == 'docs'
Requires-Dist: mkdocs-autorefs ; extra == 'docs'
Requires-Dist: mkdocs-material ; extra == 'docs'
Requires-Dist: mkdocstrings ; extra == 'docs'
Requires-Dist: mkdocstrings-python ; extra == 'docs'
